seagulls/devtools/__init__.py
seagulls/devtools/_cli_entry_point.py
seagulls/devtools/_cli_plugin.py
seagulls/devtools/_di_container.py
seagulls/devtools/_flake8_command.py
seagulls/devtools/_mypy_command.py
seagulls/devtools/_pytest_command.py
seagulls_devtools-0.1.0rc1.dist-info/entry_points.txt
seagulls_devtools-0.1.0rc1.dist-info/WHEEL
seagulls_devtools-0.1.0rc1.dist-info/METADATA
seagulls_devtools-0.1.0rc1.dist-info/RECORD
