Metadata-Version: 2.1
Name: seagulls-devtools
Version: 0.1.0rc1
Summary: 
License: MIT
Author: Lorenzo Pisani
Author-email: zeelot3k@gmail.com
Requires-Python: >=3.8,<4.0
Classifier: License :: OSI Approved :: MIT License
Classifier: Programming Language :: Python :: 3
Classifier: Programming Language :: Python :: 3.10
Classifier: Programming Language :: Python :: 3.8
Classifier: Programming Language :: Python :: 3.9
Provides-Extra: dev
Requires-Dist: colorlog
Requires-Dist: flake8
Requires-Dist: isort
Requires-Dist: mkdocs
Requires-Dist: mkdocs-awesome-pages-plugin
Requires-Dist: mkdocs-material
Requires-Dist: mypy
Requires-Dist: pdoc
Requires-Dist: pytest
Requires-Dist: pytest-cov
Requires-Dist: seagulls-engine[cli]
